<Items>
  <Item name="Broodmother Cells" identifier="broodmotherCellsAegis" description="A tissue sample from a broodmother. Could be cultured into organs" category="Medical" scale="0.5" maxstacksize="1" maxstacksizecharacterinventory="1" useinhealthinterface="False" applyTreatment="True" cargocontaineridentifier="organcrate" Tags="smallitem, medical">
    <InventoryIcon texture="%ModDir%/transplants/organs/broodmother/broodmotherCells.png" sourcerect="0,0,48,48" origin="0.5,0.5" />
    <Sprite texture="%ModDir%/transplants/organs/broodmother/broodmotherCells.png" sourcerect="0,0,48,48" depth="0.6" origin="0.5,0.5" />
    <Body width="48" height="48" density="20" />
    <Deconstruct time="120" requireddeconstructor="alienIncubator">
      <Item identifier="broodmotherLiverAegis" requiredotheritem="livertransplant" />
      <Item identifier="broodmotherLiverAegis" requiredotheritem="livertransplant_q1" />
    </Deconstruct>
   <Price baseprice="120" soldbydefault="false"></Price>
    <Holdable slots="Any,RightHand,LeftHand" handle="0.5,0.5" msg="ItemMsgPickUpUse" holdangle="90">
      <StatusEffect type="Always" target="This" condition="-0.005" conditionalComparison="And">
        <Conditional hastag="neq refrigerated" targetcontainer="true" />
        <Conditional hastag="neq medicalfabricator" Locked="neq true" targetitemcomponent="ItemContainer" targetcontainer="true" />
      </StatusEffect>
      <StatusEffect type="OnContained" target="This" condition="0.1" comparison="and">
        <Conditional condition="gte 60" />
        <Conditional hastag="refrigerated" targetcontainer="true" />
      </StatusEffect>
      <StatusEffect type="OnBroken" target="This">
        <Remove />
      </StatusEffect>
    </Holdable>
  </Item>
</Items>
